{"keyword": "site:itsieuviet.com sửa máy tính quận 3", "serp_urls": [], "titles": [], "snippets": [], "features": {"serp_quality": {"valid_result_count": 0, "target_result_count": 10, "mixed_intent": false, "ambiguous_keyword": false}}, "source": "none", "country": "vn", "language": "vi", "device": "desktop", "fetched_at": "2026-04-30T04:41:23.042880+00:00", "serp_cache_digest": "f587b03896f8fef0a1d49f43ec2dc87f692f4618d9a679f1afd8d5999304cecb", "domains": [], "serp_consistency": {"intent_distribution": {}, "mixed_intent": false}, "ambiguous_keyword": false, "locale": {"country": "vn", "language": "vi", "device": "desktop"}, "saved_at": "2026-04-30T04:41:23.042880+00:00"}